locate_pixelcolor_cythonmulti/LICENSE
locate_pixelcolor_cythonmulti/README.md
locate_pixelcolor_cythonmulti/__init__.py
locate_pixelcolor_cythonmulti/colorsearchcythonmulti.cp310-win_amd64.pyd
locate_pixelcolor_cythonmulti/colorsearchcythonmulti.pyx
locate_pixelcolor_cythonmulti/colorsearchcythonmultisetup.py
locate_pixelcolor_cythonmulti/requirements.txt
locate_pixelcolor_cythonmulti/thirdparty.json
locate_pixelcolor_cythonmulti-0.13.dist-info/LICENSE.rst
locate_pixelcolor_cythonmulti-0.13.dist-info/METADATA
locate_pixelcolor_cythonmulti-0.13.dist-info/WHEEL
locate_pixelcolor_cythonmulti-0.13.dist-info/top_level.txt
locate_pixelcolor_cythonmulti-0.13.dist-info/RECORD
