Metadata-Version: 2.1
Name: locate-pixelcolor-cythonmulti
Version: 0.13
Summary: Compiled Cython Code (parallel) - Detects colors in images 5-10 x faster than Numpy
Home-page: https://github.com/hansalemaos/locate_pixelcolor_cythonmulti
Author: Johannes Fischer
Author-email: aulasparticularesdealemaosp@gmail.com
License: MIT
Keywords: cython,bot,rgb,color,search
Classifier: Development Status :: 4 - Beta
Classifier: Programming Language :: Python :: 3 :: Only
Classifier: Programming Language :: Python :: 3.10
Classifier: Topic :: Software Development :: Libraries :: Python Modules
Classifier: Topic :: Utilities
License-File: LICENSE.rst
Requires-Dist: Cython
Requires-Dist: numpy
Requires-Dist: setuptools
